{
    "categories": [
      {
        "categoryId": 1,
        "categoryTitle": "Oson arab tili",
        "categoryType": "Boshqa",
        "lessonsCount": 29,
        "source": "Muhammad Sodiq Muhammad Ismoil",
        "completed": false,
        "lessons": [
          {
            "id": 1,
            "title": "So'zlarning tashkil topishi. So'z turkumlari",
            "url": "https://www.youtube.com/embed/wreWaTZC_lg?si=CCgSH5_IzG9ePWZP"
          },
          {
            "id": 2,
            "title": "Ismlarning jinsiga ko‘ra turlari. Muannas va muzakkar ismlar",
            "url": "https:///www.youtube.com/embed/BCnukwDgGFs?si=WLwzVcXk09Xu-RM9"
          },
          {
            "id": 3,
            "title": "Ismlarda son. Birlik, ikkilik va ko'plik",
            "url": "https:///www.youtube.com/embed/FAFaWI7HeEA?si=ZjWDGH6ezPaCI_jR"
          },
          {
            "id": 4,
            "title": "Ismlarda ko'plik",
            "url": "https://www.youtube.com/embed/PjhxCUOGX6M?si=RzT9s3b947cAfOoQ"
          },
          {
            "id": 5,
            "title": "Ma'rifa va nakra ismlar",
            "url": "https:///www.youtube.com/embed/vvq9BD4cm68?si=pueX_pJCbeCv-INW"
          },
          {
            "id": 6,
            "title": "Bino va e'rob tushunchasi. Mabniy va mu'rab kalimalar.",
            "url": "https:///www.youtube.com/embed/Nd1SmCpLpE4?si=iE4z24pP6YZq5xzr"
          },
          {
            "id": 7,
            "title": "Mu'rab kalimalar. E'roblarning turlari.",
            "url": "https:///www.youtube.com/embed/YgAPQlPFJd4?si=wPESLLbJ_GdB7Un2"
          },
          {
            "id": 8,
            "title": "Kalom va uning turlari. Umumiy takrorlash",
            "url": "https:///www.youtube.com/embed/jZuDdPUVyEs?si=eW73r_Pxy8GApYv7"
          },
          {
            "id": 9,
            "title": "Ismiy jumlalar. Mubtado va xabar",
            "url": "https:///www.youtube.com/embed/-BflhjLxwZI?si=Qru-CFlnbZ-ZW9vl"
          },
          {
            "id": 10,
            "title": "Kechikkan mubtado va oldin kelgan xabar",
            "url": "https:///www.youtube.com/embed/R7UijnRgIHo?si=2ZFi3up45b94kEyB"
          },
          {
            "id": 11,
            "title": "Badal (izohlovchi aniqlovchi)",
            "url": "https:///www.youtube.com/embed/r0asbbPbiVA?si=vomPX5idCZS4VySc"
          },
          {
            "id": 12,
            "title": "Mubtado, xabar va badal mavzulari bo'yicha mustahkamlash",
            "url": "https:///www.youtube.com/embed/7W1vTERnps8?si=lcm5wtmGhw4PsxPA"
          },
          {
            "id": 13,
            "title": "Birikma_olmoshlar",
            "url": "https:///www.youtube.com/embed/OZhChE2T1PU?si=yCGybUUr3UAMVInz"
          },
          {
            "id": 14,
            "title": "Izofa birikmasi qaratqichli",
            "url": "https:///www.youtube.com/embed/DaX63PuhQv8?si=0x-a4o3WLzIikP7H"
          },
          {
            "id": 15,
            "title": "Eʼrobning asliy va far'iy alomatlari",
            "url": "https:///www.youtube.com/embed/2zDz2CVrKoI?si=PoLr5oJagbBLYvIe"
          },
          {
            "id": 16,
            "title": "Mubtado, xabar, badal va izofa",
            "url": "https:///www.youtube.com/embed/BN6H4az1Bi0?si=0f78cIKpHIoBK-TT"
          },
          {
            "id": 17,
            "title": "Mavsuf va sifat Sifatlovchi aniqlovchi",
            "url": "https:///www.youtube.com/embed/OZhChE2T1PU?si=yCGybUUr3UAMVInz"
          },
          {
            "id": 18,
            "title": "Ikkilik va to'g'ri ko'plikdagi ismlarning e'robi",
            "url": "https:///www.youtube.com/embed/QjdyKa3UH6Q?si=XaBzbo3MgpBFerrc"
          },
          {
            "id": 19,
            "title": "Ikkilik va muzakkar toʻgʻri koʻplikdagi ismlarning izofasi",
            "url": "https:///www.youtube.com/embed/Ua8-uQoowyI?si=Vyr8Kl2VeG7Sj9lC"
          },
          {
            "id": 20,
            "title": "Rang va jismoniy xususiyatni ifodalaydigan...",
            "url": "https:///www.youtube.com/embed/MsaI1T8lbNk?si=V5afXazNxx4SVimD"
          },
          {
            "id": 21,
            "title": "Fe'l va uning turlari.",
            "url": "https:///www.youtube.com/embed/O9heULv-YRs?si=mX2FGMb-7EI7RSVH"
          },
          {
            "id": 22,
            "title": "Feʼllarning turlari sogʻlom va illatli feʼllar",
            "url": "https:///www.youtube.com/embed/eWNBYBL8dJw?si=MZ-44edECRgxdiiT"
          },
          {
            "id": 23,
            "title": "Sulosiy mujarrad feʼllarining birinchi bobi",
            "url": "https:///www.youtube.com/embed/QfRgWHmtTyw?si=wOTpunatpgukCqQB"
          },
          {
            "id": 24,
            "title": "Sulosiy mujarrad feʼlining oʻtgan zamon majhul nisbatda tuslanishi",
            "url": "https:///www.youtube.com/embed/K8gPmYuqyRw?si=9in9AhyQSTX2Nq4u"
          },
          {
            "id": 25,
            "title": "Sulosiy mujarrad 1-bob, hozirgi-kelasi zamon, aniq va majhul nisbati",
            "url": "https:///www.youtube.com/embed/eDZEgU5UVKY?si=PpVB69GbVwOc1JD4"
          },
          {
            "id": 26,
            "title": "Sulosiy mujarrad 1-bob, buyruq feʼllari",
            "url": "https:///www.youtube.com/embed/l7WxKg6x2vM?si=CNuTpm3V6VQnPdRU"
          },
          {
            "id": 27,
            "title": "Sulosiy mujarrad 1-bob boʻlishsiz (inkor) feʼllar",
            "url": "https:///www.youtube.com/embed/i8e-oGC4BC4?si=bXImKiRf_7eItI-m"
          },
          {
            "id": 28,
            "title": "Sifatdoshlar, ismi zamon va makon, ismu olat, ismi tafzil",
            "url": "https:///www.youtube.com/embed/J4p0G72YtSQ?si=ySZsW0JpReujBxOC"
          },
          {
            "id": 29,
            "title": "Birinchi oʻzagi hamzali feʼl. (Mahmuzul ayn)",
            "url": "https:///www.youtube.com/embed/prvhZUfrIEs?si=y0rxt2RJ1oiWy9V5"
          }
        ]
      },
      {
        "categoryId": 2,
        "categoryTitle": "Al bino",
        "categoryType": "sarf",
        "lessonsCount": 5,
        "source": "Baynul lisan",
        "completed": true,
        "lessons": [
          {
            "id": 4,
            "title": "Ismlarda ko'plik",
            "url": "https://www.youtube.com/embed/PjhxCUOGX6M?si=RzT9s3b947cAfOoQ"
          },
          {
            "id": 5,
            "title": "Ma'rifa va nakra ismlar",
            "url": "https:///www.youtube.com/embed/vvq9BD4cm68?si=pueX_pJCbeCv-INW"
          },
          {
            "id": 6,
            "title": "Bino va e'rob tushunchasi. Mabniy va mu'rab kalimalar.",
            "url": "https:///www.youtube.com/embed/Nd1SmCpLpE4?si=iE4z24pP6YZq5xzr"
          },
          {
            "id": 7,
            "title": "Mu'rab kalimalar. E'roblarning turlari.",
            "url": "https:///www.youtube.com/embed/YgAPQlPFJd4?si=wPESLLbJ_GdB7Un2"
          },
          {
            "id": 8,
            "title": "Kalom va uning turlari. Umumiy takrorlash",
            "url": "https:///www.youtube.com/embed/jZuDdPUVyEs?si=eW73r_Pxy8GApYv7"
          }
        ]
      }
    ]
  }
  